pteranodon/README.md
pteranodon/__init__.py
pteranodon/abstract_drone.py
pteranodon/simple_drone.py
pteranodon/implementations/__init__.py
pteranodon/implementations/hardware/__init__.py
pteranodon/implementations/hardware/realsense.py
pteranodon/implementations/hardware/videostream_gst.py
pteranodon/implementations/hardware/virtual_camera.py
pteranodon/implementations/networks/__init__.py
pteranodon/implementations/networks/mobilenet_v1.py
pteranodon/plugins/__init__.py
pteranodon/plugins/abstract_plugin.py
pteranodon/plugins/plugin_manager.py
pteranodon/plugins/base_plugins/__init__.py
pteranodon/plugins/base_plugins/abstract_base_plugin.py
pteranodon/plugins/base_plugins/action.py
pteranodon/plugins/base_plugins/action_server.py
pteranodon/plugins/base_plugins/calibration.py
pteranodon/plugins/base_plugins/camera.py
pteranodon/plugins/base_plugins/camera_server.py
pteranodon/plugins/base_plugins/component_information.py
pteranodon/plugins/base_plugins/component_information_server.py
pteranodon/plugins/base_plugins/core.py
pteranodon/plugins/base_plugins/failure.py
pteranodon/plugins/base_plugins/follow_me.py
pteranodon/plugins/base_plugins/ftp.py
pteranodon/plugins/base_plugins/geofence.py
pteranodon/plugins/base_plugins/gimbal.py
pteranodon/plugins/base_plugins/info.py
pteranodon/plugins/base_plugins/log_files.py
pteranodon/plugins/base_plugins/manual_control.py
pteranodon/plugins/base_plugins/mission.py
pteranodon/plugins/base_plugins/mission_raw.py
pteranodon/plugins/base_plugins/mission_raw_server.py
pteranodon/plugins/base_plugins/mocap.py
pteranodon/plugins/base_plugins/offboard.py
pteranodon/plugins/base_plugins/param.py
pteranodon/plugins/base_plugins/param_server.py
pteranodon/plugins/base_plugins/rtk.py
pteranodon/plugins/base_plugins/server_utility.py
pteranodon/plugins/base_plugins/shell.py
pteranodon/plugins/base_plugins/telemetry.py
pteranodon/plugins/base_plugins/telemetry_server.py
pteranodon/plugins/base_plugins/tracking_server.py
pteranodon-0.0.1.1.dist-info/METADATA
pteranodon-0.0.1.1.dist-info/WHEEL
pteranodon-0.0.1.1.dist-info/licenses/AUTHORS
pteranodon-0.0.1.1.dist-info/licenses/LICENSE
pteranodon-0.0.1.1.dist-info/RECORD
