Metadata-Version: 2.1
Name: pteranodon
Version: 0.0.1.1
Summary: A framework to built on top of MAVSDK which provides physical/virtual drone abstraction, abstraction for all async calls, gives the end users an arduino-eqsue interface, and provides movement and utility methods based on relative coordinate systems
Project-URL: Homepage, https://github.com/AutonoLab/pteranodon
Project-URL: Bug Tracker, https://github.com/AutonoLab/pteranodon/issues
Author-email: Justin Davis <jcdavis@mines.edu>
License-File: AUTHORS
License-File: LICENSE
Classifier: License :: OSI Approved :: MIT License
Classifier: Operating System :: OS Independent
Classifier: Programming Language :: Python :: 3
Requires-Python: >=3.8
Requires-Dist: grpcio>=1.47.0
Requires-Dist: mavsdk>=1.4.0
Requires-Dist: numpy>=1.23.0
Requires-Dist: pymavlink>=2.4.37
Requires-Dist: pyserial>=3.5
